dls_logform/__init__.py
dls_logform/__main__.py
dls_logform/_version.py
dls_logform/dls_logform.py
dls_logform/functions.py
dls_logform/version.py
dls_logform-6.0.5.dist-info/LICENSE
dls_logform-6.0.5.dist-info/METADATA
dls_logform-6.0.5.dist-info/WHEEL
dls_logform-6.0.5.dist-info/entry_points.txt
dls_logform-6.0.5.dist-info/top_level.txt
dls_logform-6.0.5.dist-info/RECORD
